setup.py
dargparse/__init__.py
dargparse/dargparse.py
dargparse.egg-info/PKG-INFO
dargparse.egg-info/SOURCES.txt
dargparse.egg-info/dependency_links.txt
dargparse.egg-info/top_level.txt