Metadata-Version: 1.0
Name: dargparse
Version: 0.2.5
Summary: Declarative command-line argument parser for python
Home-page: https://github.com/objectlabs/dargparse
Author: The MongoLab Team
Author-email: team@mongolab.com
License: MIT
Platform: UNKNOWN
